multiagent_rl_rm-0.2.0.dist-info/licenses/LICENSE
multiagent_rlrm/__init__.py
multiagent_rlrm/cli/__init__.py
multiagent_rlrm/cli/rmgen.py
multiagent_rlrm/environments/__init__.py
multiagent_rlrm/environments/frozen_lake/__init__.py
multiagent_rlrm/environments/frozen_lake/action_encoder_frozen_lake.py
multiagent_rlrm/environments/frozen_lake/config_frozen_lake.py
multiagent_rlrm/environments/frozen_lake/detect_event.py
multiagent_rlrm/environments/frozen_lake/event_context.py
multiagent_rlrm/environments/frozen_lake/frozen_lake_main.py
multiagent_rlrm/environments/frozen_lake/ma_frozen_lake.py
multiagent_rlrm/environments/frozen_lake/state_encoder_frozen_lake.py
multiagent_rlrm/environments/utils_envs/__init__.py
multiagent_rlrm/environments/utils_envs/evaluation_metrics.py
multiagent_rlrm/environments/utils_envs/mdp_vi.py
multiagent_rlrm/learning_algorithms/__init__.py
multiagent_rlrm/learning_algorithms/learning_algorithm.py
multiagent_rlrm/learning_algorithms/opsrl.py
multiagent_rlrm/learning_algorithms/qlearning.py
multiagent_rlrm/learning_algorithms/qlearning_lambda.py
multiagent_rlrm/learning_algorithms/qrmax_v2.py
multiagent_rlrm/learning_algorithms/rmax.py
multiagent_rlrm/learning_algorithms/ucbvi.py
multiagent_rlrm/multi_agent/__init__.py
multiagent_rlrm/multi_agent/action_encoder.py
multiagent_rlrm/multi_agent/action_rl.py
multiagent_rlrm/multi_agent/agent_rl.py
multiagent_rlrm/multi_agent/base_environment.py
multiagent_rlrm/multi_agent/event_detector.py
multiagent_rlrm/multi_agent/reward_machine.py
multiagent_rlrm/multi_agent/state_encoder.py
multiagent_rlrm/multi_agent/wrappers/__init__.py
multiagent_rlrm/multi_agent/wrappers/rm_environment_wrapper.py
multiagent_rlrm/render/__init__.py
multiagent_rlrm/render/heatmap.py
multiagent_rlrm/render/render.py
multiagent_rlrm/render/img/CR7.png
multiagent_rlrm/render/img/__init__.py
multiagent_rlrm/render/img/barca_.png
multiagent_rlrm/render/img/bcn_man2.png
multiagent_rlrm/render/img/buco_lab.png
multiagent_rlrm/render/img/carrucola.png
multiagent_rl_rm-0.2.0.dist-info/METADATA
multiagent_rl_rm-0.2.0.dist-info/WHEEL
multiagent_rl_rm-0.2.0.dist-info/top_level.txt
multiagent_rl_rm-0.2.0.dist-info/RECORD
