Metadata-Version: 2.4
Name: multiagent-rl-rm
Version: 0.2.0
Summary: Multi-Agent RLRM Framework
Home-page: https://github.com/Alee08/multi-agent-rl-rm
Author: Alessandro Trapasso
Author-email: Ale.trapasso8@gmail.com
License: Apache-2.0
Keywords: learning multiagent rewardmachine reinforcementlearning
Classifier: Development Status :: 3 - Alpha
Classifier: Intended Audience :: Science/Research
Classifier: Intended Audience :: Developers
Classifier: Topic :: Scientific/Engineering :: Artificial Intelligence
Classifier: License :: OSI Approved :: Apache Software License
Classifier: Programming Language :: Python :: 3.8
Classifier: Programming Language :: Python :: 3.9
Classifier: Programming Language :: Python :: 3.10
Classifier: Programming Language :: Python :: 3.11
Requires-Python: >=3.8
License-File: LICENSE
Requires-Dist: gymnasium==0.29.1
Requires-Dist: imageio==2.34.0
Requires-Dist: matplotlib==3.8.3
Requires-Dist: numpy==1.26.4
Requires-Dist: opencv-python==4.9.0.80
Requires-Dist: pandas==2.2.1
Requires-Dist: pettingzoo==1.24.3
Requires-Dist: pillow==10.2.0
Requires-Dist: pygame==2.5.2
Requires-Dist: scipy==1.12.0
Requires-Dist: seaborn==0.13.2
Requires-Dist: tqdm==4.66.2
Requires-Dist: unified-planning==1.1.0
Requires-Dist: wandb==0.18.7
Provides-Extra: data-analysis
Requires-Dist: pandas==2.2.1; extra == "data-analysis"
Requires-Dist: seaborn==0.13.2; extra == "data-analysis"
Requires-Dist: scipy==1.12.0; extra == "data-analysis"
Provides-Extra: image-processing
Requires-Dist: opencv-python==4.9.0.80; extra == "image-processing"
Requires-Dist: pillow==10.2.0; extra == "image-processing"
Provides-Extra: metrics-monitoring
Requires-Dist: wandb==0.18.7; extra == "metrics-monitoring"
Dynamic: author
Dynamic: author-email
Dynamic: classifier
Dynamic: description
Dynamic: description-content-type
Dynamic: home-page
Dynamic: keywords
Dynamic: license
Dynamic: license-file
Dynamic: provides-extra
Dynamic: requires-dist
Dynamic: requires-python
Dynamic: summary
